LICENSE
MANIFEST.in
readme.md
setup.py
nosmpl/__init__.py
nosmpl/body_models.py
nosmpl/box_trans.py
nosmpl/constants.py
nosmpl/geometry.py
nosmpl/geometry_np.py
nosmpl/kinematics.py
nosmpl/lbs.py
nosmpl/pose2d.py
nosmpl/smpl.py
nosmpl/smpl_onnx.py
nosmpl/star.py
nosmpl/utils.py
nosmpl/vertex_ids.py
nosmpl/vertex_joint_selector.py
nosmpl.egg-info/PKG-INFO
nosmpl.egg-info/SOURCES.txt
nosmpl.egg-info/dependency_links.txt
nosmpl.egg-info/requires.txt
nosmpl.egg-info/top_level.txt
nosmpl/data/J_regressor_h36m.npy
nosmpl/ik/__init__.py
nosmpl/ik/simple_ik.py
nosmpl/smoother/__init__.py
nosmpl/smoother/filters.py
nosmpl/smoother/smooth_filter.py
nosmpl/vis/__init__.py
nosmpl/vis/vis_o3d.py
nosmpl/vpose/__init__.py
nosmpl/vpose/tgm.py
nosmpl/vpose/vposer.py
nosmpl/vpose/tools/__init__.py
nosmpl/vpose/tools/model_loader.py
nosmpl/vpose/tools/omni_tools.py
nosmpl/vpose/tools/training_tools.py