Metadata-Version: 2.1
Name: nosmpl
Version: 0.1.4
Summary: NoSMPL: Optimized common used SMPL operation.
Home-page: https://github.com/jinfagang/nosmpl
Author: Lucas Jin
Author-email: 11@qq.com
Classifier: Programming Language :: Python :: 2
Classifier: Programming Language :: Python :: 3
Classifier: License :: Other/Proprietary License
Classifier: Operating System :: OS Independent
License-File: LICENSE
